setup.cfg
setup.py
buildout-devel/bootstrap.py
buildout-devel/buildout.cfg
src/buildout/__init__.py
src/buildout.removeaddledeggs.egg-info/PKG-INFO
src/buildout.removeaddledeggs.egg-info/SOURCES.txt
src/buildout.removeaddledeggs.egg-info/dependency_links.txt
src/buildout.removeaddledeggs.egg-info/entry_points.txt
src/buildout.removeaddledeggs.egg-info/namespace_packages.txt
src/buildout.removeaddledeggs.egg-info/not-zip-safe
src/buildout.removeaddledeggs.egg-info/requires.txt
src/buildout.removeaddledeggs.egg-info/top_level.txt
src/buildout/removeaddledeggs/__init__.py
src/docs/CHANGES.txt
src/docs/CONTRIBUTORS.txt
src/docs/README.txt
src/docs/TODOS.txt