Metadata-Version: 1.0
Name: buildout.removeaddledeggs
Version: 0.1
Summary: Removes unneeded eggs automatically from file system
Home-page: http://svn.plone.org/svn/collective/buildout/buildout.removeaddledeggs
Author: Benjamin Hedrich
Author-email: kiwisauce@pagenotfound.de
License: GPL
Keywords: buildout extension egg remove
Platform: UNKNOWN
Classifier: Framework :: Buildout
Classifier: Intended Audience :: Developers
Classifier: Topic :: Software Development :: Build Tools
Classifier: Topic :: Software Development :: Libraries :: Python Modules
